blksprs/__init__.py
blksprs/layouting/distribution_layout.py
blksprs/layouting/sparsity_layout.py
blksprs/ops/conversion.py
blksprs/ops/distribution.py
blksprs/ops/flow.py
blksprs/ops/matmul.py
blksprs/ops/partitioning.py
blksprs/ops/repeat.py
blksprs/ops/softmax.py
blksprs/ops/transpose.py
blksprs/ops/misc/broadcast_ops.py
blksprs/ops/misc/row_wise.py
blksprs/utils/autotuning.py
blksprs/utils/benchmarking.py
blksprs/utils/blksprs_tensor.py
blksprs/utils/processing.py
blksprs/utils/tools.py
blksprs/utils/validation.py
blksprs-2.1.10.dist-info/METADATA
blksprs-2.1.10.dist-info/WHEEL
blksprs-2.1.10.dist-info/top_level.txt
blksprs-2.1.10.dist-info/RECORD
