Metadata-Version: 2.4
Name: blksprs
Version: 2.1.10
Summary: A lightweight library for operations on block-sparse matrices in PyTorch.
Author-email: Felix Schön <schoen@kr.tuwien.ac.at>
Project-URL: Homepage, https://github.com/FelixSchoen/blksprs
Project-URL: Bugtracker, https://github.com/FelixSchoen/blksprs/issues
Requires-Python: >=3.11
Requires-Dist: torch>=2.8.0
Requires-Dist: numpy
Provides-Extra: test
Requires-Dist: pytest; extra == "test"
Requires-Dist: pytest-xdist; extra == "test"
Requires-Dist: pytest-cov; extra == "test"
Requires-Dist: coverage; extra == "test"
Requires-Dist: build; extra == "test"
Requires-Dist: matplotlib; extra == "test"
